pyconverters_whisperx/__init__.py
pyconverters_whisperx/whisperx.py
pyconverters_whisperx-0.5.34.dist-info/entry_points.txt
pyconverters_whisperx-0.5.34.dist-info/licenses/LICENSE
pyconverters_whisperx-0.5.34.dist-info/WHEEL
pyconverters_whisperx-0.5.34.dist-info/METADATA
pyconverters_whisperx-0.5.34.dist-info/RECORD
